origottlieb/__init__.py
origottlieb-0.0.2.dist-info/METADATA
origottlieb-0.0.2.dist-info/WHEEL
origottlieb-0.0.2.dist-info/top_level.txt
origottlieb-0.0.2.dist-info/RECORD
