Metadata-Version: 2.1
Name: origottlieb
Version: 0.0.2
Summary: The beautiest
Home-page: https://github.com/MyUser/MyProject
Author: ItayGo
Author-email: itaygonen797@example.com
Classifier: Programming Language :: Python :: 3
Classifier: License :: OSI Approved :: MIT License
Classifier: Operating System :: OS Independent
Requires-Python: >=3.6
